hg_systematic/__init__.py
hg_systematic/data/__init__.py
hg_systematic/data/generators.py
hg_systematic/impl/__init__.py
hg_systematic/impl/_calendar_impl.py
hg_systematic/impl/_price_impl.py
hg_systematic/impl/_rolling_rules_impl.py
hg_systematic/index/README.md
hg_systematic/index/__init__.py
hg_systematic/index/configuration.py
hg_systematic/index/configuration_service.py
hg_systematic/index/conversion.py
hg_systematic/index/pricing_service.py
hg_systematic/index/single_asset_index.py
hg_systematic/index/units.py
hg_systematic/operators/__init__.py
hg_systematic/operators/_calendar.py
hg_systematic/operators/_index.py
hg_systematic/operators/_price.py
hg_systematic/operators/_rolling_rules.py
hg_systematic-0.23.dist-info/LICENSE
hg_systematic-0.23.dist-info/METADATA
hg_systematic-0.23.dist-info/WHEEL
hg_systematic-0.23.dist-info/entry_points.txt
hg_systematic-0.23.dist-info/RECORD
