Metadata-Version: 2.3
Name: hg_systematic
Version: 0.23
Summary:  A library and examples to show how HGraph can be used for systematic trading. 
License: MIT
Keywords: reactive,graph,fpg,forward propogating graph,time series,functional reactive programming,frp,functional,time-series,systematic,trading,strategy
Author: Howard Henson
Author-email: howard@henson.me.uk
Requires-Python: >=3.11
Classifier: Development Status :: 3 - Alpha
Classifier: License :: OSI Approved :: MIT License
Classifier: Programming Language :: Python
Classifier: Programming Language :: Python :: 3
Classifier: Programming Language :: Python :: 3.11
Classifier: Programming Language :: Python :: 3.12
Classifier: Programming Language :: Python :: 3.13
Classifier: Programming Language :: Python :: Implementation :: CPython
Requires-Dist: frozendict (>=2.3.10)
Requires-Dist: hg_oap (>=0.1.13)
Requires-Dist: hgraph (>=0.4.13)
Requires-Dist: importlib_resources
Requires-Dist: matplotlib
Requires-Dist: numpy (>=1.23)
Requires-Dist: ordered-set (>=4.1.0)
Requires-Dist: polars (>=1.0)
Requires-Dist: sortedcontainers (>=2.4.0)
Project-URL: Changelog, https://github.com/hhenson/hg_systematic/blob/main/CHANGELOG.md
Project-URL: Documentation, https://github.com/hhenson/hg_systematic/blob/main/README.md
Project-URL: Homepage, https://github.com/hhenson/hg_systematic
Project-URL: Issues, https://github.com/hhenson/hg_systematic/blob/main/ISSUES.md
Project-URL: Repository, https://github.com/hhenson/hg_systematic.git
